{
  "text": {
    "id": "7c592086-deb9-4362-8e86-9d3b39747f59",
    "cefr_level": "A2",
    "text_id": "text_001",
    "text_translated": "Between 100,000 and 50,000 years ago, things changed. We see signs of the first people living together. For example, we see paintings in caves. No one knows the link between this and language. Brains did not get bigger. But people became smarter and did more things. Did using language make their brains get better? Or did their smarter brains start to make language?",
    "version": 2,
    "created_at": "2025-08-31 17:58:36.577069",
    "updated_at": "2025-08-31 17:58:36.577080"
  },
  "feedback": {
    "id": "5cd50a01-5057-4fb5-ab24-7a6e7ccbe0f1",
    "approval": "PASS",
    "grade": 10,
    "feedback": "PASS: The feedback is exemplary. It is direct, specific, and actionable. It correctly identifies multiple failure points, such as 'Meaning Preservation Failure' and 'Grammar Violation'. It provides clear evidence by citing specific phrases like ''people living together'' and explains the underlying grammatical rule violation. The inclusion of a 'Suggestion' with concrete examples for correction makes the feedback exceptionally useful.",
    "created_at": "2025-08-31 17:59:08.018964"
  }
}