{
  "text": {
    "id": "5c0b3e3b-37a0-43d1-a3be-f2f36ec6c066",
    "cefr_level": "B1",
    "text_id": "text_001",
    "text_translated": "During the last two centuries, improvements in technology and health meant that fewer children died young, which caused rapid population growth because these large families had more children who survived into adulthood. However, since contraception (methods used to prevent having a baby) became more widely available in the 1960s, the global average number of babies per woman has declined from six to as low as two.",
    "version": 10,
    "created_at": "2025-08-30 18:54:51.261883",
    "updated_at": "2025-08-30 18:54:51.261892"
  },
  "feedback": {
    "id": "6e0850d5-93f9-412a-bb13-312a6081a7e4",
    "approval": "PASS",
    "grade": 10,
    "feedback": "The JSON object is a perfect response. The feedback is direct, blunt, and concise. It clearly states the reason for failure ('The text's linguistic complexity was classified as B2') and provides specific, actionable evidence ('a long, multi-clause sentence', 'B2-level vocabulary ('widely')'). The approval and grade are perfectly aligned with the feedback.",
    "created_at": "2025-08-30 18:55:14.502048"
  }
}